# Chapter 08 Exercise 08

## Question

Compile the `Person` and `SecretAgent` classes in Section 8.6, “Overriding Fields,” on page 89 and analyze the class files with `javap`. How many name fields are there? How many name getter methods are there? What do they get? (Hint: Use the `-c` and `-private` options.)

## Solution

```
Warning: Binary file Ch08Ex08_Person contains scala4impatient.chapter08.Ch08Ex08_Person
Compiled from "Ch08Ex08_SecretAgent.scala"
public class scala4impatient.chapter08.Ch08Ex08_Person {
  private final java.lang.String name;

  public java.lang.String name();
    Code:
       0: aload_0
       1: getfield      #13                 // Field name:Ljava/lang/String;
       4: areturn

  public java.lang.String toString();
    Code:
       0: new           #18                 // class scala/collection/mutable/StringBuilder
       3: dup
       4: invokespecial #22                 // Method scala/collection/mutable/StringBuilder."<init>":()V
       7: aload_0
       8: invokevirtual #26                 // Method java/lang/Object.getClass:()Ljava/lang/Class;
      11: invokevirtual #31                 // Method java/lang/Class.getName:()Ljava/lang/String;
      14: invokevirtual #35                 // Method scala/collection/mutable/StringBuilder.append:(Ljava/lang/Object;)Lscala/collection/mutable/StringBuilder;
      17: ldc           #37                 // String [name=
      19: invokevirtual #35                 // Method scala/collection/mutable/StringBuilder.append:(Ljava/lang/Object;)Lscala/collection/mutable/StringBuilder;
      22: aload_0
      23: invokevirtual #39                 // Method name:()Ljava/lang/String;
      26: invokevirtual #35                 // Method scala/collection/mutable/StringBuilder.append:(Ljava/lang/Object;)Lscala/collection/mutable/StringBuilder;
      29: ldc           #41                 // String ]
      31: invokevirtual #35                 // Method scala/collection/mutable/StringBuilder.append:(Ljava/lang/Object;)Lscala/collection/mutable/StringBuilder;
      34: invokevirtual #43                 // Method scala/collection/mutable/StringBuilder.toString:()Ljava/lang/String;
      37: areturn

  public scala4impatient.chapter08.Ch08Ex08_Person(java.lang.String);
    Code:
       0: aload_0
       1: aload_1
       2: putfield      #13                 // Field name:Ljava/lang/String;
       5: aload_0
       6: invokespecial #45                 // Method java/lang/Object."<init>":()V
       9: return
}
```

```
Warning: Binary file Ch08Ex08_SecretAgent contains scala4impatient.chapter08.Ch08Ex08_SecretAgent
Compiled from "Ch08Ex08_SecretAgent.scala"
public class scala4impatient.chapter08.Ch08Ex08_SecretAgent extends scala4impatient.chapter08.Ch08Ex08_Person {
  private final java.lang.String name;

  public java.lang.String name();
    Code:
       0: aload_0
       1: getfield      #13                 // Field name:Ljava/lang/String;
       4: areturn

  public scala4impatient.chapter08.Ch08Ex08_SecretAgent(java.lang.String);
    Code:
       0: aload_0
       1: aload_1
       2: invokespecial #19                 // Method scala4impatient/chapter08/Ch08Ex08_Person."<init>":(Ljava/lang/String;)V
       5: aload_0
       6: ldc           #21                 // String secret
       8: putfield      #13                 // Field name:Ljava/lang/String;
      11: return
}
```
